fast_rs/__init__.py
fast_rs/rs.py
fast_rs/util.py
fast_rs-0.2.0.dist-info/licenses/LICENSE
fast_rs-0.2.0.dist-info/METADATA
fast_rs-0.2.0.dist-info/WHEEL
fast_rs-0.2.0.dist-info/top_level.txt
fast_rs-0.2.0.dist-info/RECORD
