Metadata-Version: 2.4
Name: fast_rs
Version: 0.2.0
Summary: Fast sphericity and roundness in 2D and 3D using local thickness
Author-email: Pawel Tomasz Pieta <papi@dtu.dk>
License-Expression: MIT
Project-URL: Homepage, https://github.com/PaPieta/fast_rs
Project-URL: Issues, https://github.com/PaPieta/fast_rs/issues
Classifier: Programming Language :: Python :: 3
Classifier: Operating System :: OS Independent
Requires-Python: >=3.8
License-File: LICENSE
Requires-Dist: localthickness
Requires-Dist: numpy
Requires-Dist: scipy
Requires-Dist: scikit-image
Dynamic: license-file
